basic_image_eda/__init__.py
basic_image_eda/__version__.py
basic_image_eda/eda.py
basic_image_eda-0.0.3.dist-info/LICENSE
basic_image_eda-0.0.3.dist-info/METADATA
basic_image_eda-0.0.3.dist-info/WHEEL
basic_image_eda-0.0.3.dist-info/entry_points.txt
basic_image_eda-0.0.3.dist-info/top_level.txt
basic_image_eda-0.0.3.dist-info/RECORD
