Metadata-Version: 2.1
Name: basic-image-eda
Version: 0.0.3
Summary: image dataset eda tool to check basic information of images.
Home-page: https://github.com/Soongja/basic-image-eda
Author: Seungjae Kim
Author-email: sjn735@gmail.com
License: MIT
Platform: UNKNOWN
